jupyterlab_collaborative_chat/__init__.py
jupyterlab_collaborative_chat/_version.py
jupyterlab_collaborative_chat/ychat.py
jupyterlab_collaborative_chat/tests/__init__.py
jupyterlab_collaborative_chat/tests/test_ychat.py
jupyterlab_collaborative_chat-0.5.0.data/data/etc/jupyter/jupyter_server_config.d/jupyterlab_collaborative_chat.json
jupyterlab_collaborative_chat-0.5.0.data/data/share/jupyter/labextensions/jupyterlab-collaborative-chat-extension/package.json
jupyterlab_collaborative_chat-0.5.0.data/data/share/jupyter/labextensions/jupyterlab-collaborative-chat-extension/schemas/jupyterlab-collaborative-chat-extension/chat-panel.json
jupyterlab_collaborative_chat-0.5.0.data/data/share/jupyter/labextensions/jupyterlab-collaborative-chat-extension/schemas/jupyterlab-collaborative-chat-extension/commands.json
jupyterlab_collaborative_chat-0.5.0.data/data/share/jupyter/labextensions/jupyterlab-collaborative-chat-extension/schemas/jupyterlab-collaborative-chat-extension/factory.json
jupyterlab_collaborative_chat-0.5.0.data/data/share/jupyter/labextensions/jupyterlab-collaborative-chat-extension/schemas/jupyterlab-collaborative-chat-extension/package.json.orig
jupyterlab_collaborative_chat-0.5.0.data/data/share/jupyter/labextensions/jupyterlab-collaborative-chat-extension/static/119.1f3f2f51baaba7427867.js
jupyterlab_collaborative_chat-0.5.0.data/data/share/jupyter/labextensions/jupyterlab-collaborative-chat-extension/static/36.4fef76b0dc881098f3ec.js
jupyterlab_collaborative_chat-0.5.0.data/data/share/jupyter/labextensions/jupyterlab-collaborative-chat-extension/static/432.0336e784e6f958a4e408.js
jupyterlab_collaborative_chat-0.5.0.data/data/share/jupyter/labextensions/jupyterlab-collaborative-chat-extension/static/509.44ba1a3941982437ce8f.js
jupyterlab_collaborative_chat-0.5.0.data/data/share/jupyter/labextensions/jupyterlab-collaborative-chat-extension/static/77.7a35bf2531291550e10c.js
jupyterlab_collaborative_chat-0.5.0.dist-info/METADATA
jupyterlab_collaborative_chat-0.5.0.dist-info/WHEEL
jupyterlab_collaborative_chat-0.5.0.dist-info/entry_points.txt
jupyterlab_collaborative_chat-0.5.0.dist-info/licenses/LICENSE
jupyterlab_collaborative_chat-0.5.0.dist-info/RECORD
