Metadata-Version: 2.3
Name: jupyterlab_collaborative_chat
Version: 0.5.0
Dynamic: Keywords
Summary: A chat extension based on shared documents
Project-URL: Homepage, https://github.com/jupyterlab/jupyter-chat
Project-URL: Bug Tracker, https://github.com/jupyterlab/jupyter-chat/issues
Project-URL: Repository, https://github.com/jupyterlab/jupyter-chat.git
Author-email: Jupyter Development Team <jupyter@googlegroups.com>
License: BSD 3-Clause License
License-File: LICENSE
Classifier: Framework :: Jupyter
Classifier: Framework :: Jupyter :: JupyterLab
Classifier: Framework :: Jupyter :: JupyterLab :: 4
Classifier: Framework :: Jupyter :: JupyterLab :: Extensions
Classifier: Framework :: Jupyter :: JupyterLab :: Extensions :: Prebuilt
Classifier: License :: OSI Approved :: BSD License
Classifier: Programming Language :: Python
Classifier: Programming Language :: Python :: 3
Classifier: Programming Language :: Python :: 3.8
Classifier: Programming Language :: Python :: 3.9
Classifier: Programming Language :: Python :: 3.10
Classifier: Programming Language :: Python :: 3.11
Classifier: Programming Language :: Python :: 3.12
Requires-Python: >=3.8
Requires-Dist: jupyter-collaboration<3,>=2.1.4
Requires-Dist: jupyter-server<3,>=2.0.1
Requires-Dist: jupyter-ydoc
Requires-Dist: jupyterlab~=4.0
Requires-Dist: pycrdt
Provides-Extra: test
Requires-Dist: coverage; extra == 'test'
Requires-Dist: pytest; extra == 'test'
Requires-Dist: pytest-asyncio; extra == 'test'
Requires-Dist: pytest-cov; extra == 'test'
Requires-Dist: pytest-jupyter[server]>=0.6.0; extra == 'test'
